Metadata-Version: 1.0
Name: aiogmailsender
Version: 0.0.3
Summary: Asynchronous Gmail Client
Home-page: https://github.com/babjo/aiogmailsender
Author: babjo
Author-email: UNKNOWN
License: UNKNOWN
Platform: UNKNOWN
